Exercicios/ex26/ex26.v
module add2_bits(ABCD, XYZ);
  input [3:0] ABCD;
  output [2:0] XYZ;

  assign XYZ = ABCD[3:2] + ABCD[1:0];

endmodule

Exercicios/ex26/ex26_testbench.v
module ex26_testbench;
  reg [3:0] a;
  wire [2:0] s;

  localparam period=20;

  add2_bits adder(a, s);

  initial begin
    $dumpfile("ex26.vcd");
    $dumpvars;
    
    $display("\n===========  Simulation output begins =====\n");
    $monitor(" MONITOR_1 At %0d ns A=2'b%b A=2'b%b S=3'b%b ", $time, a[3:2], a[1:0], s);
    
    a = 4'b0000;
    #period;

    a = 4'b0001;
    #period;

    a = 4'b0010;
    #period;
    
    a = 4'b0011;
    #period;
    
    $monitor(" MONITOR_2 At %0d ns A=2'b%b A=2'b%b S=3'b%b ", $time, a[3:2], a[1:0], s);

    a = 4'b0100;
    #period;

    a = 4'b0101;
    #period;

    a = 4'b0110;
    #period;

    a = 4'b0111;
    #period;

    $monitor(" MONITOR_3 At %0d ns A=2'b%b A=2'b%b S=3'b%b ", $time, a[3:2], a[1:0], s);

    a = 4'b1000;
    #period;

    a = 4'b1001;
    #period;

    a = 4'b1010;
    #period;

    a = 4'b1011;
    #period;

    $monitor(" MONITOR_4 At %0d ns A=2'b%b A=2'b%b S=3'b%b ", $time, a[3:2], a[1:0], s);

    a = 4'b1100;
    #period;

    a = 4'b1101;
    #period;

    a = 4'b1110;
    #period;

    a = 4'b1111;
    #period;

    $display("\n===========  Simulation output ends     =====\n");
	  $finish;
  
  end

endmodule

Exercicios/ex26/ex26.vcd
$date
	Thu Sep 12 10:00:13 2019
$end
$version
	Icarus Verilog
$end
$timescale
	1s
$end
$scope module ex26_testbench $end
$var wire 3 ! s [2:0] $end
$var reg 4 " a [3:0] $end
$scope module adder $end
$var wire 4 # ABCD [3:0] $end
$var wire 3 $ XYZ [2:0] $end
$upscope $end
$upscope $end
$enddefinitions $end
#0
$dumpvars
b0 $
b0 #
b0 "
b0 !
$end
#20
b1 !
b1 $
b1 "
b1 #
#40
b10 !
b10 $
b10 "
b10 #
#60
b11 !
b11 $
b11 "
b11 #
#80
b1 !
b1 $
b100 "
b100 #
#100
b10 !
b10 $
b101 "
b101 #
#120
b11 !
b11 $
b110 "
b110 #
#140
b100 !
b100 $
b111 "
b111 #
#160
b10 !
b10 $
b1000 "
b1000 #
#180
b11 !
b11 $
b1001 "
b1001 #
#200
b100 !
b100 $
b1010 "
b1010 #
#220
b101 !
b101 $
b1011 "
b1011 #
#240
b11 !
b11 $
b1100 "
b1100 #
#260
b100 !
b100 $
b1101 "
b1101 #
#280
b101 !
b101 $
b1110 "
b1110 #
#300
b110 !
b110 $
b1111 "
b1111 #
